syphonpy/__init__.py
syphonpy/setup.py
syphonpy/tester.py
syphonpy_mschuff0881-0.0.1.dist-info/METADATA
syphonpy_mschuff0881-0.0.1.dist-info/WHEEL
syphonpy_mschuff0881-0.0.1.dist-info/top_level.txt
syphonpy_mschuff0881-0.0.1.dist-info/RECORD
