Metadata-Version: 2.1
Name: syphonpy-mschuff0881
Version: 0.0.1
Summary: Python bindings for the Syphon Framework (OSX)
Home-page: https://github.com/njazz/syphonpy
Author: njazz
Author-email: 
License: UNKNOWN
Platform: UNKNOWN
Classifier: Programming Language :: Python :: 3
Classifier: License :: OSI Approved :: MIT License
Classifier: Operating System :: OS Independent
Requires-Python: >=3.6
